hanguk/__init__.py
hanguk/app.py
hanguk/static/data.json
hanguk-2.0.0.dist-info/LICENSE
hanguk-2.0.0.dist-info/METADATA
hanguk-2.0.0.dist-info/WHEEL
hanguk-2.0.0.dist-info/top_level.txt
hanguk-2.0.0.dist-info/RECORD
