Metadata-Version: 2.1
Name: hanguk
Version: 2.0.0
Summary: The official Korean language romanization system in Python.
Author-email: joumaico <joumaico@gmx.com>
License: MIT License
Project-URL: Homepage, https://github.com/joumaico/hanguk
Classifier: License :: OSI Approved :: MIT License
Classifier: Programming Language :: Python
Classifier: Programming Language :: Python :: 3
Requires-Python: >=3.10
License-File: LICENSE
